odoo9_addon_business_requirement-9.0.1.0.0.99.dev13-py2.7-nspkg.pth
odoo_addons/business_requirement/__openerp__.py
odoo_addons/business_requirement/menu_items.xml
odoo_addons/business_requirement/__init__.py
odoo_addons/business_requirement/README.rst
odoo_addons/business_requirement/security/security.xml
odoo_addons/business_requirement/security/ir.model.access.csv
odoo_addons/business_requirement/models/business_requirement_category.py
odoo_addons/business_requirement/models/business_requirement.py
odoo_addons/business_requirement/models/project.py
odoo_addons/business_requirement/models/__init__.py
odoo_addons/business_requirement/views/business_requirement_category_view.xml
odoo_addons/business_requirement/views/project.xml
odoo_addons/business_requirement/views/business_requirement_view.xml
odoo_addons/business_requirement/data/business_data.xml
odoo_addons/business_requirement/tests/__init__.py
odoo_addons/business_requirement/tests/test_project.py
odoo_addons/business_requirement/tests/test_br.py
odoo_addons/business_requirement/static/img/bus_req_done.png
odoo_addons/business_requirement/static/img/bus_req_tags.png
odoo_addons/business_requirement/static/img/bus_req_cust_story.png
odoo_addons/business_requirement/static/img/bus_req_tags2.png
odoo_addons/business_requirement/static/img/bus_req_alias.png
odoo_addons/business_requirement/static/img/br_workflow.graphml
odoo_addons/business_requirement/static/img/bus_req.png
odoo_addons/business_requirement/static/img/bus_req_cancel.png
odoo_addons/business_requirement/static/img/bus_req_drop.png
odoo_addons/business_requirement/static/img/bus_req_approved.png
odoo_addons/business_requirement/static/img/module_diag.graphml
odoo_addons/business_requirement/static/img/bus_req_confirmed.png
odoo_addons/business_requirement/static/img/bus_req_workflow.png
odoo_addons/business_requirement/static/img/bus_req_module_diag.png
odoo_addons/business_requirement/static/img/bus_req_tree.png
odoo9_addon_business_requirement-9.0.1.0.0.99.dev13.dist-info/top_level.txt
odoo9_addon_business_requirement-9.0.1.0.0.99.dev13.dist-info/WHEEL
odoo9_addon_business_requirement-9.0.1.0.0.99.dev13.dist-info/RECORD
odoo9_addon_business_requirement-9.0.1.0.0.99.dev13.dist-info/metadata.json
odoo9_addon_business_requirement-9.0.1.0.0.99.dev13.dist-info/DESCRIPTION.rst
odoo9_addon_business_requirement-9.0.1.0.0.99.dev13.dist-info/METADATA
odoo9_addon_business_requirement-9.0.1.0.0.99.dev13.dist-info/namespace_packages.txt
